CHANGES.txt
README.txt
bootstrap.py
setup.cfg
setup.py
solr-3.5.cfg
docs/LICENSE.GPL
docs/LICENSE.txt
docs/Makefile
docs/make.bat
docs/source/conf.py
docs/source/index.rst
src/bg/__init__.py
src/bg.crawler.egg-info/PKG-INFO
src/bg.crawler.egg-info/SOURCES.txt
src/bg.crawler.egg-info/dependency_links.txt
src/bg.crawler.egg-info/entry_points.txt
src/bg.crawler.egg-info/namespace_packages.txt
src/bg.crawler.egg-info/not-zip-safe
src/bg.crawler.egg-info/requires.txt
src/bg.crawler.egg-info/top_level.txt
src/bg/crawler/__init__.py
src/bg/crawler/crawler.py
src/bg/crawler/header.txt
src/bg/crawler/logger.py
templates/logging.properties.tmpl