Metadata-Version: 1.0
Name: bg.crawler
Version: 0.2.6
Summary: Crawler for importing data from a filesystem directory into Solr
Home-page: http://pypi.python.org/pypi/bg.crawler
Author: Andreas Jung
Author-email: info@zopyx.com
License: GPL
Keywords: Solr Python Fulltext Crawler
Platform: UNKNOWN
Classifier: Programming Language :: Python
